mifiel/__init__.py
mifiel/api_auth/__init__.py
mifiel/api_auth/api_auth.py
mifiel/api_auth/context_manager.py
mifiel/api_auth/requests_api_auth.py
mifiel/api_auth/signature.py
mifiel/base.py
mifiel/certificate.py
mifiel/client.py
mifiel/document.py
mifiel/response.py
mifiel/template.py
mifiel-0.0.13.dist-info/LICENSE.txt
mifiel-0.0.13.dist-info/WHEEL
mifiel-0.0.13.dist-info/METADATA
mifiel-0.0.13.dist-info/RECORD
