Metadata-Version: 2.1
Name: mifiel
Version: 0.0.13
Summary: Python API Client library for mifiel.com
Home-page: http://github.com/mifiel/python-api-client
Author: Genaro Madrid
Author-email: genmadrid@gmail.com
Requires-Python: >=3.5
Classifier: Programming Language :: Python :: 3
Classifier: Programming Language :: Python :: 3.5
Classifier: Programming Language :: Python :: 3.6
Classifier: Programming Language :: Python :: 3.7
Classifier: Programming Language :: Python :: 3.8
Classifier: Programming Language :: Python :: 3.9
Requires-Dist: requests (>=2.20.0)
Project-URL: Documentation, http://docs.mifiel.com/?python#introduction
Project-URL: Repository, http://github.com/mifiel/python-api-client
